lyceanem/__init__.py
lyceanem/_version.py
lyceanem/base_classes.py
lyceanem/base_types.py
lyceanem/electromagnetics/__init__.py
lyceanem/electromagnetics/antenna_utilities.py
lyceanem/electromagnetics/beamforming.py
lyceanem/electromagnetics/empropagation.py
lyceanem/electromagnetics/sources.py
lyceanem/geometry/__init__.py
lyceanem/geometry/geometryfunctions.py
lyceanem/geometry/parabolas.scad
lyceanem/geometry/targets.py
lyceanem/geometry/data/NasaAlmondHalfWavelengthv2.stl
lyceanem/geometry/data/NasaAlmondQuarterWavelengthv2.stl
lyceanem/geometry/data/NasaAlmondTenthWavelengthv2.stl
lyceanem/models/__init__.py
lyceanem/models/frequency_domain.py
lyceanem/models/time_domain.py
lyceanem/raycasting/__init__.py
lyceanem/raycasting/rayfunctions.py
lyceanem/tests/__init__.py
lyceanem/tests/reflectordata.py
lyceanem/tests/test_base_classes.py
lyceanem/tests/test_empropagation.py
lyceanem/tests/test_geometryfunctions.py
lyceanem/tests/data/Medium_Reference_Plate_Covered_Normal_1_plan_grid_0p5mm.txt
lyceanem/tests/data/UAV.stl
lyceanem/tests/data/UAVarray.stl
lyceanem/tests/data/__init__.py
lyceanem/tests/data/plate_copper.mat
lyceanem/tests/data/prototypescanpoints24GHztenthwavelength.ply
lyceanem/tests/data/referencescanpoints24GHztenthwavelength.ply
lyceanem/utility/math_functions.py
lyceanem-0.5.dist-info/LICENSE.txt
lyceanem-0.5.dist-info/METADATA
lyceanem-0.5.dist-info/WHEEL
lyceanem-0.5.dist-info/top_level.txt
lyceanem-0.5.dist-info/zip-safe
lyceanem-0.5.dist-info/RECORD
